m0m/__init__.py
m0m/verbs.json
m0m-0.0.0b2.dist-info/LICENSE.txt
m0m-0.0.0b2.dist-info/METADATA
m0m-0.0.0b2.dist-info/WHEEL
m0m-0.0.0b2.dist-info/top_level.txt
m0m-0.0.0b2.dist-info/RECORD
