Metadata-Version: 2.1
Name: m0m
Version: 0.0.0b2
Summary: With m0m you can offend someone's mother!
Home-page: UNKNOWN
Author: 34Mx
Author-email: 34mx.development@gmail.com
License: MIT
Keywords: python,offending
Platform: UNKNOWN
Classifier: Development Status :: 1 - Planning
Classifier: Intended Audience :: Developers
Classifier: Operating System :: Microsoft :: Windows :: Windows 10
Classifier: License :: OSI Approved :: MIT License
Classifier: Programming Language :: Python :: 3
